CM23137UNO/__init__.py
CM23137UNO/lineales.py
CM23137UNO/no_lineales.py
cm23137uno-0.3.dist-info/licenses/LICENSE
cm23137uno-0.3.dist-info/METADATA
cm23137uno-0.3.dist-info/WHEEL
cm23137uno-0.3.dist-info/top_level.txt
cm23137uno-0.3.dist-info/RECORD
