Metadata-Version: 2.4
Name: CM23137UNO
Version: 0.3
Summary: Librería para resolver sistemas de ecuaciones lineales y no lineales.
Author: Manuel Carballo
Author-email: CM23137@ues.edu.sv
License: MIT
Classifier: Programming Language :: Python :: 3
Classifier: License :: OSI Approved :: MIT License
Classifier: Programming Language :: Python :: 3.9
Classifier: Programming Language :: Python :: 3.10
Classifier: Programming Language :: Python :: 3.11
License-File: LICENSE
Requires-Dist: numpy
Dynamic: author
Dynamic: author-email
Dynamic: classifier
Dynamic: description
Dynamic: description-content-type
Dynamic: license
Dynamic: license-file
Dynamic: requires-dist
Dynamic: summary
